nicecoding/__init__.py
nicecoding/password_make.py
nicecoding-0.0.3.dist-info/METADATA
nicecoding-0.0.3.dist-info/WHEEL
nicecoding-0.0.3.dist-info/top_level.txt
nicecoding-0.0.3.dist-info/RECORD
