Metadata-Version: 2.1
Name: nicecoding
Version: 0.0.3
Summary: Strong Password make package
Home-page: https://github.com/nicecoding1/
Author: Jaesang Jo
Author-email: nicecoding@naver.com
License: UNKNOWN
Platform: UNKNOWN
Classifier: Programming Language :: Python :: 3
Classifier: License :: OSI Approved :: MIT License
Classifier: Operating System :: OS Independent
Requires-Python: >=3.6
